README.txt
setup.py
oii/__init__.py
oii.egg-info/PKG-INFO
oii.egg-info/SOURCES.txt
oii.egg-info/dependency_links.txt
oii.egg-info/top_level.txt