Metadata-Version: 1.0
Name: oii
Version: 0.11
Summary: myself odoo tools
Home-page: UNKNOWN
Author: yeyu
Author-email: zwgmlr3@outlook.com
License: UNKNOWN
Platform: UNKNOWN
